{"id":13142,"date":"2017-05-03T13:44:20","date_gmt":"2017-05-03T11:44:20","guid":{"rendered":"https:\/\/www.bistrorawvegan.com\/restaurant\/abonament-raw-vegan-fara-gluten-ciorna\/"},"modified":"2021-04-08T20:05:31","modified_gmt":"2021-04-08T17:05:31","slug":"abonament-vegan-fara-gluten","status":"publish","type":"product","link":"https:\/\/bistrorawvegan.com\/produs\/abonament-vegan-fara-gluten\/","title":{"rendered":"VEGAN &#8211; F\u0102R\u0102 GLUTEN 28 lei\/zi &#8211; minim 5 zile"},"content":{"rendered":"","protected":false},"excerpt":{"rendered":"<div class=\"woocommerce-product-details__short-description\">\n<p><span style=\"color: #008000;\"><strong>Aboneaz\u0103-te la s\u0103n\u0103tate.<\/strong><\/span><\/p>\n<p><span style=\"color: #000000;\">Tu alegi ce con\u021bine meniul t\u0103u zilnic: fie c\u0103 vrei sup\u0103, fel principal, cin\u0103, aperitiv, desert sau suc.<\/span><\/p>\n<p><span style=\"color: #008000;\"><strong>Tot ce trebuie s\u0103 faci este s\u0103 configurezi un meniu de minimum 28 lei\/zi<\/strong>.<\/span><\/p>\n<p><span style=\"color: #000000;\">Mai mult dec\u00e2t at\u00e2t, <strong>po\u021bi alege<\/strong> din fiecare produs <strong>mai multe por\u021bii<\/strong> (poate \u00ee\u021bi place ceva foarte mult).<\/span><\/p>\n<p><span style=\"color: #000000;\">G\u0103tim special pentru tine \u0219i livr\u0103m m\u00e2ncarea cald\u0103 \u00een Caserole BIO, acas\u0103 sau la birou. Dac\u0103 vrei s\u0103 venim de M\u00c2INE la tine, te rug\u0103m s\u0103 plasezi comanda AZI p\u00e2n\u0103 \u00een ora 21:00.<\/span><\/p>\n<p><span style=\"color: #008000;\">Meniul pentru urm\u0103toarele zile \u00eel g\u0103se\u0219ti mai jos. Te rug\u0103m s\u0103 cite\u015fti \u00een josul paginii la Descriere Produs\u00a0 detalii legate de orele de livrare, \u00eentreb\u0103ri si r\u0103spunsuri legate de abonamente.<\/span><\/p>\n<\/div>\n","protected":false},"featured_media":23443,"comment_status":"open","ping_status":"closed","template":"","meta":[],"_links":{"self":[{"href":"https:\/\/bistrorawvegan.com\/wp-json\/wp\/v2\/product\/13142"}],"collection":[{"href":"https:\/\/bistrorawvegan.com\/wp-json\/wp\/v2\/product"}],"about":[{"href":"https:\/\/bistrorawvegan.com\/wp-json\/wp\/v2\/types\/product"}],"replies":[{"embeddable":true,"href":"https:\/\/bistrorawvegan.com\/wp-json\/wp\/v2\/comments?post=13142"}],"wp:featuredmedia":[{"embeddable":true,"href":"https:\/\/bistrorawvegan.com\/wp-json\/wp\/v2\/media\/23443"}],"wp:attachment":[{"href":"https:\/\/bistrorawvegan.com\/wp-json\/wp\/v2\/media?parent=13142"}],"curies":[{"name":"wp","href":"https:\/\/api.w.org\/{rel}","templated":true}]}}